{
  "submission_id": "S92",
  "user_id": "U1",
  "problem_id": "P11",
  "timestamp": "2025-10-09T05:40:12Z",
  "status": "Running... (Testcase 8)",
  "language": "python",
  "test_results": [
    {
      "test_case_number": 1,
      "status": "passed",
      "message": "Test case passed",
      "execution_time": 0.01,
      "memory_usage": 7.98046875,
      "actual_output": "2",
      "expected_output": "2",
      "input": "5698 4838\n"
    },
    {
      "test_case_number": 2,
      "status": "passed",
      "message": "Test case passed",
      "execution_time": 0.06,
      "memory_usage": 8.02734375,
      "actual_output": "3",
      "expected_output": "3",
      "input": "46926 42591\n"
    },
    {
      "test_case_number": 3,
      "status": "passed",
      "message": "Test case passed",
      "execution_time": 0.01,
      "memory_usage": 8.19921875,
      "actual_output": "3",
      "expected_output": "3",
      "input": "1953 192\n"
    },
    {
      "test_case_number": 4,
      "status": "passed",
      "message": "Test case passed",
      "execution_time": 0.01,
      "memory_usage": 8.0625,
      "actual_output": "1",
      "expected_output": "1",
      "input": "41906 7297\n"
    },
    {
      "test_case_number": 5,
      "status": "passed",
      "message": "Test case passed",
      "execution_time": 0.03,
      "memory_usage": 8.09375,
      "actual_output": "1",
      "expected_output": "1",
      "input": "1 1\n"
    },
    {
      "test_case_number": 6,
      "status": "passed",
      "message": "Test case passed",
      "execution_time": 0.01,
      "memory_usage": 7.75390625,
      "actual_output": "2",
      "expected_output": "2",
      "input": "48266 6718\n"
    },
    {
      "test_case_number": 7,
      "status": "passed",
      "message": "Test case passed",
      "execution_time": 0.05,
      "memory_usage": 8.171875,
      "actual_output": "2",
      "expected_output": "2",
      "input": "36782 13032\n"
    },
    {
      "test_case_number": 8,
      "status": "passed",
      "message": "Test case passed",
      "execution_time": 0.01,
      "memory_usage": 8.06640625,
      "actual_output": "50",
      "expected_output": "50",
      "input": "100 50\n"
    }
  ]
}